mvf1/__init__.py
mvf1/cmdline.py
mvf1/mcp.py
mvf1/mvf1.py
mvf1/mvf1_schema.py
mvf1-2.0.1.dist-info/licenses/LICENSE
mvf1-2.0.1.dist-info/METADATA
mvf1-2.0.1.dist-info/WHEEL
mvf1-2.0.1.dist-info/entry_points.txt
mvf1-2.0.1.dist-info/top_level.txt
mvf1-2.0.1.dist-info/RECORD
