Metadata-Version: 2.4
Name: mvf1
Version: 2.0.1
Summary: A Python package and MCP server to control video players for MultiViewer, the best way to watch motorsports like Formula 1.
Author-email: Rob Spectre <rob@brooklynhacker.com>
License: MIT
Project-URL: Homepage, https://github.com/RobSpectre/mvf1
Project-URL: Repository, https://github.com/RobSpectre/mvf1
Project-URL: Bug Tracker, https://github.com/RobSpectre/mvf1/issues
Keywords: multiviewer,formula1,mcp,video,motorsports
Classifier: Programming Language :: Python :: 3
Classifier: License :: OSI Approved :: MIT License
Classifier: Operating System :: OS Independent
Classifier: Development Status :: 5 - Production/Stable
Classifier: Intended Audience :: Developers
Classifier: Natural Language :: English
Classifier: Environment :: Console
Requires-Python: >=3.10
License-File: LICENSE
Requires-Dist: click
Requires-Dist: sgqlc
Requires-Dist: fastmcp
Dynamic: license-file
